MANIFEST.in
README.rst
Requirements.txt
setup.py
Curtains.egg-info/PKG-INFO
Curtains.egg-info/SOURCES.txt
Curtains.egg-info/dependency_links.txt
Curtains.egg-info/entry_points.txt
Curtains.egg-info/not-zip-safe
Curtains.egg-info/requires.txt
Curtains.egg-info/top_level.txt
curtains/__init__.py
curtains/__main__.py
curtains/api.py
curtains/decorator.py
curtains/main.py
curtains/operations.py
curtains/osspecific.py
curtains/state.py
curtains/utils.py
test/__init__.py
test/test_osspecific.py
test/test_utils.py