Metadata-Version: 1.1
Name: Curtains
Version: 0.3.1
Summary:  A command line tool for remote execution, application deployment and system administration in the Windows environment (as of now) without using SSH.
Home-page: https://github.com/gouthambs/Curtains
Author: Gouthaman Balaraman
Author-email: gouthaman.balaraman@gmail.com
License: MIT
Platform: win
Classifier: Development Status :: 4 - Beta
Classifier: Environment :: Console
Classifier: Intended Audience :: Developers
Classifier: Intended Audience :: System Administrators
Classifier: License :: OSI Approved :: MIT License
Classifier: Operating System :: Microsoft
Classifier: Programming Language :: Python
Classifier: Programming Language :: Python :: 3
Classifier: Programming Language :: Python :: 3.5
Classifier: Topic :: Software Development
Classifier: Topic :: Software Development :: Build Tools
Classifier: Topic :: Software Development :: Libraries
Classifier: Topic :: Software Development :: Libraries :: Python Modules
Classifier: Topic :: System :: Clustering
Classifier: Topic :: System :: Software Distribution
Classifier: Topic :: System :: Systems Administration
